{
    "id": "90c699f6-403e-4e64-8e28-e2813c76c8f2",
    "title": "Akkanthai",
    "slug": null,
    "state": "public",
    "isWip": null,
    "isDraft": null,
    "entityClass": "Marker",
    "icon": "fa-solid fa-location-dot",
    "url": null,
    "subscribergroups": [],
    "folderId": null,
    "tags": "",
    "updateDate": null,
    "description": null,
    "position": null,
    "htmlMarker": null,
    "seeded": null,
    "creationDate": {
        "date": "2024-10-21 01:41:31.000000",
        "timezone_type": 3,
        "timezone": "Europe/London"
    },
    "isDeleted": null,
    "type": null,
    "isDirectLink": false,
    "isDraggable": false,
    "labelTitle": null,
    "labelType": "label-default",
    "className": null,
    "geoX": 1433,
    "geoY": 3075,
    "geoZ": null,
    "polygonPoints": null,
    "circleRadius": 145,
    "linePoints": null,
    "lineColor": null,
    "lineWeight": 4,
    "lineOpacity": null,
    "lineDash": "",
    "colorOutline": "#ff0000",
    "colorFill": "#ff0000",
    "opacityOutline": 50,
    "opacityFill": 50,
    "isEditable": true,
    "success": true
}